{
  "id": 15,
  "country": "AT",
  "broadcaster": "ORF",
  "artist": "Marianne Mendt",
  "artistPeople": [
    "Marianne Mendt"
  ],
  "song": "Musik",
  "videoUrls": [
    "https://www.youtube-nocookie.com/embed/WeO5piPgTes",
    "https://www.youtube-nocookie.com/embed/Ln2dwJ0g18c",
    "https://www.youtube-nocookie.com/embed/N43Szx3h1Yc",
    "https://www.youtube-nocookie.com/embed/kwWHUQM9Odo"
  ],
  "bpm": 126,
  "tone": "E minor",
  "backings": null,
  "commentators": [
    "Ernst Grissemann"
  ],
  "composers": null,
  "conductor": "Robert Opratko",
  "dancers": null,
  "lyricists": null,
  "spokesperson": null,
  "stageDirector": null,
  "writers": [
    "Manuel Rigoni",
    "Richard Schönherz"
  ]
}