{
  "id": 0,
  "country": "MT",
  "artist": "Gaia Cauchi",
  "song": "The Start",
  "videoUrls": [
    "https://www.youtube-nocookie.com/embed/thje0DAh_lU",
    "https://www.youtube-nocookie.com/embed/W7wjtE1VBQk"
  ],
  "bpm": 95,
  "tone": "Ab major",
  "artistPeople": [
    "Gaia Cauchi"
  ],
  "backings": null,
  "dancers": null,
  "stageDirector": null,
  "composers": [
    "Elton Zarb",
    "Gaia Cauchi",
    "Gillian Attard"
  ],
  "conductor": null,
  "lyricists": [
    "Gaia Cauchi",
    "Matt Muxu"
  ],
  "writers": null,
  "broadcaster": null,
  "commentators": null,
  "jury": null,
  "spokesperson": null
}