{
  "id": 1,
  "country": "IE",
  "broadcaster": "RTÉ",
  "artist": "Marc Roberts",
  "artistPeople": [
    "Séan Hegarty"
  ],
  "song": "Mysterious Woman",
  "videoUrls": [
    "https://www.youtube-nocookie.com/embed/GV_3B13Q3xs",
    "https://www.youtube-nocookie.com/embed/-DJ4EVJ5jxM"
  ],
  "bpm": 145,
  "tone": "G major",
  "backings": null,
  "commentators": [
    "Pat Kenny"
  ],
  "composers": null,
  "conductor": null,
  "dancers": null,
  "lyricists": null,
  "spokesperson": "Eileen Dunne",
  "stageDirector": null,
  "writers": [
    "John Farry"
  ]
}