{
  "id": 8,
  "country": "CY",
  "broadcaster": "CyBC",
  "artist": "Elena Patroclou",
  "artistPeople": [
    "Elena Patroklou"
  ],
  "song": "S.O.S.",
  "videoUrls": [
    "https://www.youtube-nocookie.com/embed/Qf2fLGTlwR4",
    "https://www.youtube-nocookie.com/embed/wwSoju8Mqfg",
    "https://www.youtube-nocookie.com/embed/ilidvftZpjE"
  ],
  "bpm": 137,
  "tone": "A major",
  "backings": [
    "Alexandros Panayi",
    "Dalida Mitzi",
    "Nassia Trachonitou"
  ],
  "commentators": [
    "Evi Papamichail"
  ],
  "composers": [
    "Kypros Charalambus"
  ],
  "conductor": "Alexandros Kyros Zografou",
  "dancers": null,
  "lyricists": [
    "Andreas Christou"
  ],
  "spokesperson": "Anna Partelidou",
  "stageDirector": null,
  "writers": null
}