{
  "id": 6,
  "country": "RS",
  "broadcaster": null,
  "artist": "Lena Stamenković",
  "artistPeople": [
    "Lena Stamenković"
  ],
  "song": "Lenina pesma",
  "videoUrls": [
    "https://www.youtube-nocookie.com/embed/R7AUTZfy-0E",
    "https://www.youtube-nocookie.com/embed/NcaFIW1M7Z8"
  ],
  "bpm": 91,
  "tone": "E major",
  "backings": null,
  "commentators": null,
  "composers": [
    "Leontina Vukomanović"
  ],
  "conductor": null,
  "dancers": null,
  "lyricists": [
    "Lena Stamenković",
    "Leontina Vukomanović"
  ],
  "spokesperson": null,
  "stageDirector": null,
  "writers": null
}