{
  "id": 13,
  "country": "AL",
  "broadcaster": null,
  "artist": "Anna Gjebrea",
  "artistPeople": [
    "Anna Gjebrea"
  ],
  "song": "Stand By You",
  "videoUrls": [
    "https://www.youtube-nocookie.com/embed/YASU8NPu7dw",
    "https://www.youtube-nocookie.com/embed/0kJkmkADrSU"
  ],
  "bpm": 194,
  "tone": "C# major",
  "backings": null,
  "commentators": null,
  "composers": null,
  "conductor": null,
  "dancers": null,
  "lyricists": null,
  "spokesperson": null,
  "stageDirector": null,
  "writers": [
    "Adam Watts",
    "Endi Çuçi",
    "Gannin Arnold",
    "Sanni M'Mairura"
  ]
}