{
  "id": 23,
  "country": "ES",
  "artist": "Melody",
  "song": "Esa diva",
  "videoUrls": [
    "https://www.youtube-nocookie.com/embed/IEKSa9FVLqA",
    "https://www.youtube-nocookie.com/embed/_sfZ4L8pGzQ",
    "https://www.youtube-nocookie.com/embed/H46FB-rLh04",
    "https://www.youtube-nocookie.com/embed/2J9xYVcP4MA",
    "https://www.youtube-nocookie.com/embed/PqOeAnGX1eg",
    "https://www.youtube-nocookie.com/embed/6gB3HSVD1nc",
    "https://www.youtube-nocookie.com/embed/P-qp57jp10k"
  ],
  "bpm": 127,
  "tone": "F# major",
  "artistPeople": [
    "Melodía Ruiz Gutiérrez"
  ],
  "backings": null,
  "dancers": [
    "Alex Bullón",
    "Ana Acosta",
    "Iván Matías Urquiaga",
    "Marc Montojo",
    "Vicky Gómez"
  ],
  "stageDirector": "Mario Crea",
  "composers": null,
  "conductor": null,
  "lyricists": null,
  "writers": [
    "Alberto Fuentes Lorite",
    "Melody"
  ],
  "broadcaster": "TVE",
  "commentators": [
    "Julia Varela",
    "Sònia Urbano",
    "Tony Aguilar",
    "Xavi Martínez"
  ],
  "jury": [
    "Anabel Conde",
    "Irene Garrido Miñano",
    "Javier Llano Abril",
    "Javier Pageo",
    "María Melodía Pérez Castillo"
  ],
  "spokesperson": "Chanel Terrero"
}