{
  "id": 5,
  "country": "SE",
  "artist": "Family Four",
  "song": "Vita vidder",
  "videoUrls": [
    "https://www.youtube-nocookie.com/embed/Mq10KQ77dnY",
    "https://www.youtube-nocookie.com/embed/U7LkF7OzxmU",
    "https://www.youtube-nocookie.com/embed/EUaTl7Zoo3k",
    "https://www.youtube-nocookie.com/embed/6PLblelGO2Q"
  ],
  "bpm": 120,
  "tone": "G major",
  "artistPeople": [
    "Agneta Munther",
    "Berndt Öst",
    "Marie Bergman",
    "Pierre Isacsson"
  ],
  "backings": null,
  "dancers": null,
  "stageDirector": null,
  "composers": null,
  "conductor": "Claes Rosendahl",
  "lyricists": null,
  "writers": [
    "Håkan Elmquist"
  ],
  "broadcaster": "SR",
  "commentators": [
    "Åke Strömmer"
  ],
  "jury": null,
  "spokesperson": null
}